viping/VIPG5encode.py
viping/__init__.py
VIPG5encode-0.0.1.dist-info/LICENSE
VIPG5encode-0.0.1.dist-info/METADATA
VIPG5encode-0.0.1.dist-info/WHEEL
VIPG5encode-0.0.1.dist-info/top_level.txt
VIPG5encode-0.0.1.dist-info/RECORD
