Metadata-Version: 2.1
Name: VIPG5encode
Version: 0.0.1
Summary: This is to encrypt tools or files or words
Home-page: https://github.com/Team-G5/G5vipencode
Author: Example Author
Author-email: Glitch5@hotmail.com
License: UNKNOWN
Project-URL: Bug Tracker, https://github.com/Team-G5/G5vipencode/issues/1
Platform: UNKNOWN
Classifier: Programming Language :: Python :: 3.7
Classifier: License :: OSI Approved :: MIT License
Classifier: Operating System :: OS Independent
Requires-Python: >=3.6
License-File: LICENSE
